x2cdict/__init__.py
x2cdict/db/__init__.py
x2cdict/db/db.py
x2cdict/db/de2cn.py
x2cdict/db/en2cn.py
x2cdict/db/es2cn.py
x2cdict/deeplearning.py
x2cdict/dictapi.py
x2cdict/entry.py
x2cdict/google.py
x2cdict/lib.py
x2cdict/posmap.py
x2cdict/qishe.py
x2cdict-0.1.48.dist-info/METADATA
x2cdict-0.1.48.dist-info/WHEEL
x2cdict-0.1.48.dist-info/entry_points.txt
x2cdict-0.1.48.dist-info/RECORD
