Metadata-Version: 2.1
Name: x2cdict
Version: 0.1.48
Summary: translate X language into Chinese
Home-page: https://github.com/qishe-nlp/x2cdict
Keywords: language,dictionary,Chinese
Author: Phoenix Grey
Author-email: phoenix.grey0108@gmail.com
Requires-Python: >=3.8,<4.0
Classifier: Programming Language :: Python :: 3
Classifier: Programming Language :: Python :: 3.8
Classifier: Programming Language :: Python :: 3.9
Classifier: Programming Language :: Python :: 3.10
Classifier: Programming Language :: Python :: 3.11
Classifier: Programming Language :: Python :: 3.12
Requires-Dist: click (>=8.0.3,<9.0.0)
Requires-Dist: deepl (>=1.3.1,<2.0.0)
Requires-Dist: googletrans (==4.0.0-rc1)
Requires-Dist: pymongo (>=3.10.1,<4.0.0)
Project-URL: Repository, https://github.com/qishe-nlp/x2cdict
